pct_sdk/__init__.py
pct_sdk/cas.py
pct_sdk/chain.py
pct_sdk/core.py
pct_sdk/opa.py
pct_sdk/policy.py
pct_sdk/sign.py
proofcarryingthought_sdk-0.1.0.dist-info/METADATA
proofcarryingthought_sdk-0.1.0.dist-info/WHEEL
proofcarryingthought_sdk-0.1.0.dist-info/licenses/LICENSE
proofcarryingthought_sdk-0.1.0.dist-info/RECORD
