Metadata-Version: 2.4
Name: proofcarryingthought-sdk
Version: 0.1.0
Summary: Minimal Proof-Carrying Thought (PCT) SDK: canonical bytes, Merkle, CAS, optional Ed25519 signing, policy gates, and chain-of-custody.
Project-URL: Homepage, https://github.com/Maverick0351a/ProofCarryingThought-SDK
Project-URL: Repository, https://github.com/Maverick0351a/ProofCarryingThought-SDK
Author-email: PCT <pct@example.com>
License: Apache-2.0
License-File: LICENSE
Keywords: cas,ed25519,merkle,pct,security,verification
Classifier: License :: OSI Approved :: Apache Software License
Classifier: Operating System :: OS Independent
Classifier: Programming Language :: Python :: 3
Requires-Python: >=3.8
Provides-Extra: crypto
Requires-Dist: pynacl>=1.5; extra == 'crypto'
Provides-Extra: dcbor
Requires-Dist: cbor2>=5.6; extra == 'dcbor'
Provides-Extra: dev
Requires-Dist: pytest>=7; extra == 'dev'
Requires-Dist: ruff>=0.5; extra == 'dev'
